make_a_video_pytorch/__init__.py
make_a_video_pytorch/attend.py
make_a_video_pytorch/make_a_video.py
make_a_video_pytorch-0.4.0.dist-info/LICENSE
make_a_video_pytorch-0.4.0.dist-info/METADATA
make_a_video_pytorch-0.4.0.dist-info/WHEEL
make_a_video_pytorch-0.4.0.dist-info/top_level.txt
make_a_video_pytorch-0.4.0.dist-info/RECORD
