Metadata-Version: 2.1
Name: make-a-video-pytorch
Version: 0.4.0
Summary: Make-A-Video - Pytorch
Home-page: https://github.com/lucidrains/make-a-video-pytorch
Author: Phil Wang
Author-email: lucidrains@gmail.com
License: MIT
Keywords: artificial intelligence,deep learning,attention mechanism,text-to-video,axial convolutions
Classifier: Development Status :: 4 - Beta
Classifier: Intended Audience :: Developers
Classifier: Topic :: Scientific/Engineering :: Artificial Intelligence
Classifier: License :: OSI Approved :: MIT License
Classifier: Programming Language :: Python :: 3.6
License-File: LICENSE
Requires-Dist: classifier-free-guidance-pytorch
Requires-Dist: einops >=0.6
Requires-Dist: torch >=1.6
